sbpars/__init__.py
sbpars/app.py
sbpars/scripts/sbpars.py
sbpars-0.3.0.dist-info/entry_points.txt
sbpars-0.3.0.dist-info/METADATA
sbpars-0.3.0.dist-info/WHEEL
sbpars-0.3.0.dist-info/RECORD
