Metadata-Version: 2.1
Name: sbpars
Version: 0.3.0
Summary: 
Author: qmka
Author-email: eidolonzx@gmail.com
Requires-Python: >=3.10,<4.0
Classifier: Programming Language :: Python :: 3
Classifier: Programming Language :: Python :: 3.10
Classifier: Programming Language :: Python :: 3.11
Requires-Dist: bs4 (>=0.0.1,<0.0.2)
Requires-Dist: flake8 (>=6.0.0,<7.0.0)
Requires-Dist: openpyxl (>=3.0.10,<4.0.0)
Requires-Dist: pandas (>=1.5.2,<2.0.0)
